<program>



<assignment>
<variable>
<var_name>a</var_name>
</variable>
<value>
<constant>10</constant>
</value>
</assignment>



<if>
<condition>
<variable>
<var_name>a</var_name>
</variable>
<operator>g</operator>
<constant>10</constant>
</condition>
</if>
<body>



<if>
<condition>
<variable>
<var_name>a</var_name>
</variable>
<operator>g</operator>
<constant>7</constant>
</condition>
</if>
<body>



<if>
<condition>
<variable>
<var_name>a</var_name>
</variable>
<operator>l</operator>
<constant>9</constant>
</condition>
</if>
<body>



<print>
<expression>
<string>Hi</string>
</expression>
</print>
</body>



<elif>
<condition>
<variable>
<var_name>a</var_name>
</variable>
<operator>l</operator>
<constant>8</constant>
</condition>
</elif>
<body>



<print>
<expression>
<string>No</string>
</expression>
</print>
</body>



<else></else>
<body>



<print>
<expression>
<string>Nah</string>
</expression>
</print>
</body>
</body>



<else></else>
<body>



<print>
<expression>
<string>Bebe</string>
</expression>
</print>
</body>
</body>



<else></else>
<body>



<print>
<expression>
<string>Nope</string>
</expression>
</print>
</body>
</program>
